{
    "name": "Control Surface (fork with BLE name mods)",
    "version": "2.1.1",
    "description": "Arduino library for creating MIDI controllers and other MIDI devices. (forked to add BLE manufacturer + model names)",
    "keywords": [
        "midi",
        "midi-controller",
        "midi-over-usb",
        "usb",
        "midi-over-ble",
        "bluetooth",
        "vu-meter",
        "oled"
    ],
    "repository": {
        "type": "git",
        "url": "https://github.com/z-l-p/Control-Surface-with-BLE-mods"
    },
    "authors": [
        {
            "name": "Pieter P (forked by z-l-p)",
            "maintainer": true
        }
    ],
    "license": "GPL-3.0-or-later",
    "export": {
        "exclude": [
            ".github",
            "build",
            "docs",
            "doxygen",
            "mock",
            "scripts",
            "test",
            "tools"
        ]
    },
    "frameworks": "arduino",
    "platforms": [
        "atmelavr",
        "atmelmegaavr",
        "atmelsam",
        "espressif32",
        "espressif8266",
        "nordicnrf52",
        "teensy",
        "renesas-ra",
        "raspberrypi"
    ]
}
